{
    "type": "deep-zoom",
    "options": {
        "viewport": {
            "width": 5000,
            "height": 5000
        },
        "minimapImage" : "./layer1/8/0_0.jpg"
    },
    "layers": [
        {
            "type": "deep-image",
            "title": "Layer 0",
            "color": "#ff3333",
            "opacity": 1,
            "visible": true,
            "exclusive": false,
            "previewImage": "./layer0/8/0_0.jpg",
            "imageSrc": "./layer0",
            "width": 4256,
            "height": 2832,
            "tileSize": 256,
            "tileOverlap": 1
        },
        {
            "type": "deep-image",
            "title": "Layer 1",
            "color": "#3333ff",
            "opacity": 1,
            "visible": false,
            "exclusive": false,
            "previewImage": "./layer1/8/0_0.jpg",
            "imageSrc": "./layer1",
            "width": 4256,
            "height": 6396,
            "tileSize": 256,
            "tileOverlap": 1
        },
        {
            "type": "deep-image",
            "title": "Layer 1 Copia",
            "opacity": 1,
            "visible": true,
            "exclusive": true,
            "previewImage": "./layer1/8/0_0.jpg",
            "imageSrc": "./layer1",
            "width": 4256,
            "height": 6396,
            "tileSize": 256,
            "tileOverlap": 1
        },
        {
            "type": "vector",
            "title": "Vector Layer Test",
            "color": "#ff33ff",
            "opacity": 1,
            "exclusive": false,
            "visible": true,
            "shapes": [
                {
                    "type": "polygon",
                    "title": "My Polygon",
                    "href" : "../intervento/tecnica",
                    "drawAttributes": {
                        "stroke": true,
                        "strokeColor": "rgb(255, 100, 255)",
                        "fill": true,
                        "fillColor": "rgba(255, 100, 255, 0.2)"
                    },
                    "points": [
                        [
                            0,
                            0
                        ],
                        [
                            1000,
                            0
                        ],
                        [
                            1000,
                            800
                        ],
                        [
                            100,
                            700
                        ]
                    ]
                },
                {
                    "type": "circle",
                    "title": "My Circle",
                    "drawAttributes": {
                        "stroke": true,
                        "fill": true,
                        "strokeColor": "rgb(255,0,0)",
                        "fillColor": "rgba(255,0,0,0.2)"
                    },
                    "center": [
                        2000,
                        2000
                    ],
                    "radius": 500
                }
            ]
        }
    ]
}